intellipush/__init__.py
intellipush/client.py
intellipush/contacts.py
intellipush/messages.py
intellipush/shorturls.py
intellipush/utils.py
intellipush-0.2.0.dist-info/LICENSE
intellipush-0.2.0.dist-info/METADATA
intellipush-0.2.0.dist-info/WHEEL
intellipush-0.2.0.dist-info/top_level.txt
intellipush-0.2.0.dist-info/RECORD
