Metadata-Version: 2.1
Name: intellipush
Version: 0.2.0
Summary: Client for accessing the intellipush message service.
Home-page: https://www.intellipush.com/
Author: Mats Lindh
License: UNKNOWN
Platform: UNKNOWN
Requires-Dist: requests
